split_expense/__init__.py
split_expense/app.py
splitexpense-0.1.2.dist-info/licenses/LICENSE
splitexpense-0.1.2.dist-info/METADATA
splitexpense-0.1.2.dist-info/WHEEL
splitexpense-0.1.2.dist-info/entry_points.txt
splitexpense-0.1.2.dist-info/top_level.txt
splitexpense-0.1.2.dist-info/RECORD
