Metadata-Version: 2.4
Name: splitexpense
Version: 0.1.2
Summary: A Tkinter-based app to split expenses among people and export summaries to Excel.
Author-email: "Pancham (MuddyHope)" <ljpancham@gmail.com>
License-Expression: MIT
Project-URL: Homepage, https://github.com/MuddyHope/split_expense
Project-URL: Repository, https://github.com/MuddyHope/split_expense
Keywords: split,expense,tkinter,grocery,ui
Requires-Python: >=3.7
License-File: LICENSE
Requires-Dist: pandas
Requires-Dist: openpyxl
Dynamic: license-file
